{
    "version": 1,
    "license": "this content is under ICLA licence, read more on https://wiki.imperialspace.net/icla",
    "copyright": "Sprite received from @buhoj_med, PR made by @crookielv",
    "size": {
      "x": 32,
      "y": 32
    },
      "states": [

        {
            "name": "junko"
        },
        {
            "name": "marisa"
        },
        {
            "name": "reimu"
        },
        {
            "name": "reisen"
        },
        {
            "name": "tewi"
        },
        {
            "name": "cirno"
        },
        {
            "name": "sakuya"
        },
        {
            "name": "eirin"
        },
        {
            "name": "teto"
        }
      ]
}
